{"assets/Desktop.png":["assets/Desktop.png"],"assets/airplane.png":["assets/airplane.png"],"assets/androidStudio.jpg":["assets/androidStudio.jpg"],"assets/art.jpg":["assets/art.jpg"],"assets/audio.png":["assets/audio.png"],"assets/battery.png":["assets/battery.png"],"assets/bin0.png":["assets/bin0.png"],"assets/bluetooth.png":["assets/bluetooth.png"],"assets/chrome.png":["assets/chrome.png"],"assets/doc.png":["assets/doc.png"],"assets/edge.png":["assets/edge.png"],"assets/explorer%20(1).png":["assets/explorer%20(1).png"],"assets/explorer.png":["assets/explorer.png"],"assets/facebook.png":["assets/facebook.png"],"assets/feed.png":["assets/feed.png"],"assets/git.png":["assets/git.png"],"assets/home.png":["assets/home.png"],"assets/nearshare.png":["assets/nearshare.png"],"assets/nightmode.png":["assets/nightmode.png"],"assets/paint.png":["assets/paint.png"],"assets/power.png":["assets/power.png"],"assets/ppt.png":["assets/ppt.png"],"assets/project.png":["assets/project.png"],"assets/ps.png":["assets/ps.png"],"assets/saver.png":["assets/saver.png"],"assets/search.png":["assets/search.png"],"assets/settings.png":["assets/settings.png"],"assets/sidepane.png":["assets/sidepane.png"],"assets/spotify.png":["assets/spotify.png"],"assets/store.png":["assets/store.png"],"assets/tiktok.png":["assets/tiktok.png"],"assets/user.png":["assets/user.png"],"assets/userDir.png":["assets/userDir.png"],"assets/vlc-player.png":["assets/vlc-player.png"],"assets/vs.png":["assets/vs.png"],"assets/wallpaper.jpg":["assets/wallpaper.jpg"],"assets/weather.png":["assets/weather.png"],"assets/widget.png":["assets/widget.png"],"assets/wifi.png":["assets/wifi.png"],"assets/word.png":["assets/word.png"],"packages/cupertino_icons/assets/CupertinoIcons.ttf":["packages/cupertino_icons/assets/CupertinoIcons.ttf"]}